MANIFEST.in
README.md
requirements.txt
setup.py
Autolive/__init__.py
Autolive/__main__.py
Autolive/autolive.py
Autolive/channel.py
Autolive/ladder_generator.py
autolive.egg-info/PKG-INFO
autolive.egg-info/SOURCES.txt
autolive.egg-info/dependency_links.txt
autolive.egg-info/entry_points.txt
autolive.egg-info/not-zip-safe
autolive.egg-info/requires.txt
autolive.egg-info/top_level.txt