Metadata-Version: 1.2
Name: autolive
Version: 0.0.3
Summary: Dev Package for autolive
Home-page: https://github.com/pabloVoorvaart/Autolive.git
Author: Pablo Voorvaart
Author-email: pablo.voorvaart@gmail.com
License: MIT
Platform: UNKNOWN
Classifier: Programming Language :: Python :: 3
Classifier: License :: OSI Approved :: MIT License
Classifier: Operating System :: OS Independent
Requires-Python: >=3.6
